
{"items":[{"name":"DUE Platform","href":"intro.html","topicHref":"intro.html"},{"name":"Getting Started","href":"getting-started.html","topicHref":"getting-started.html"},{"name":"DUE Script","href":"due-script/due-script.html","topicHref":"due-script/due-script.html","items":[{"name":"DUE Console","href":"console.html","topicHref":"console.html"},{"name":"Core Library","href":"due-script/corelib/corelib.html","topicHref":"due-script/corelib/corelib.html","items":[{"name":"Analog","href":"due-script/corelib/analog.html","topicHref":"due-script/corelib/analog.html"},{"name":"Beep","href":"due-script/corelib/beep.html","topicHref":"due-script/corelib/beep.html"},{"name":"Button","href":"due-script/corelib/button.html","topicHref":"due-script/corelib/button.html"},{"name":"Digital","href":"due-script/corelib/digital.html","topicHref":"due-script/corelib/digital.html"},{"name":"Distance","href":"due-script/corelib/distance.html","topicHref":"due-script/corelib/distance.html"},{"name":"Frequency","href":"due-script/corelib/frequency.html","topicHref":"due-script/corelib/frequency.html"},{"name":"I2C","href":"due-script/corelib/i2c.html","topicHref":"due-script/corelib/i2c.html"},{"name":"Infrared","href":"due-script/corelib/infrared.html","topicHref":"due-script/corelib/infrared.html"},{"name":"LCD","href":"due-script/corelib/lcd.html","topicHref":"due-script/corelib/lcd.html"},{"name":"LED","href":"due-script/corelib/led.html","topicHref":"due-script/corelib/led.html"},{"name":"NeoPixel","href":"due-script/corelib/neopixel.html","topicHref":"due-script/corelib/neopixel.html"},{"name":"Servo","href":"due-script/corelib/servo.html","topicHref":"due-script/corelib/servo.html"},{"name":"SPI","href":"due-script/corelib/spi.html","topicHref":"due-script/corelib/spi.html"},{"name":"System","href":"due-script/corelib/systemfunctions.html","topicHref":"due-script/corelib/systemfunctions.html"},{"name":"Temp-Humidity","href":"due-script/corelib/temp-humidity.html","topicHref":"due-script/corelib/temp-humidity.html"},{"name":"Touch","href":"due-script/corelib/touch.html","topicHref":"due-script/corelib/touch.html"},{"name":"UART","href":"due-script/corelib/uart.html","topicHref":"due-script/corelib/uart.html"}]},{"name":"Samples","href":"due-script/samples/samples.html","topicHref":"due-script/samples/samples.html","items":[{"name":"Basic Examples","href":"due-script/samples/basic.html","topicHref":"due-script/samples/basic.html"},{"name":"NeoPixel Matrix","href":"due-script/samples/neopixel-matrix.html","topicHref":"due-script/samples/neopixel-matrix.html"},{"name":"NeoPixel Rotary","href":"due-script/samples/rotary-neopixel.html","topicHref":"due-script/samples/rotary-neopixel.html"},{"name":"Falling Bird","href":"due-script/samples/falling-bird.html","topicHref":"due-script/samples/falling-bird.html"},{"name":"Pulse Analog Clock","href":"due-script/samples/pulse-analogclock.html","topicHref":"due-script/samples/pulse-analogclock.html"},{"name":"Pulse Bounce Ball","href":"due-script/samples/pulse-bouncingball.html","topicHref":"due-script/samples/pulse-bouncingball.html"},{"name":"BrainGamer Sketch","href":"due-script/samples/pulse-gamer-sketch.html","topicHref":"due-script/samples/pulse-gamer-sketch.html"},{"name":"BrainGamer Pong","href":"due-script/samples/pulse-gamer-pong.html","topicHref":"due-script/samples/pulse-gamer-pong.html"}]},{"name":"Streams","href":"due-script/streams.html","topicHref":"due-script/streams.html"}]},{"name":"Coding Options","href":"coding-options/coding-options.html","topicHref":"coding-options/coding-options.html","items":[{"name":"Python","href":"coding-options/python.html","topicHref":"coding-options/python.html"},{"name":"JavaScript","href":"coding-options/javascript.html","topicHref":"coding-options/javascript.html"},{"name":".NET","href":"coding-options/dotnet.html","topicHref":"coding-options/dotnet.html"},{"name":"C++","href":"coding-options/cpp.html","topicHref":"coding-options/cpp.html"},{"name":"Swift","href":"coding-options/swift.html","topicHref":"coding-options/swift.html"},{"name":"Excel","href":"coding-options/excel.html","topicHref":"coding-options/excel.html"},{"name":"Other","href":"coding-options/other.html","topicHref":"coding-options/other.html"}]},{"name":"Downloads","href":"downloads.html","topicHref":"downloads.html"},{"name":"Legal","href":"legal.html","topicHref":"legal.html"}]}
